{
  "prop": {
    "column": {
      "$ref": "../features/column.json",
      "description": {
        "en": "Relational metadata a property projects to as a DB column (foreign key, …).",
        "pt": "Metadados relacionais que uma propriedade projeta como coluna de BD (chave estrangeira, …)."
      },
      "title": {
        "en": "Column",
        "pt": "Coluna"
      }
    },
    "description": {
      "$ref": "../features/description.json",
      "description": {
        "en": "Optional localized blurb for a term (i18n text)."
      },
      "title": {
        "en": "Description",
        "pt": "Descrição"
      }
    },
    "identity": {
      "$ref": "../features/identity.json"
    },
    "measurand": {
      "$ref": "../features/measurand.json",
      "description": {
        "en": "The metrology facts of a quantity kind — its unit, SI unit, and default accumulation. The kind's enum member carries the site-agnostic defaults; a `specification` composes measurand so a device/site can OVERRIDE them. The deterministic on-bus `slug` lives on the specification's `identity`, not here."
      },
      "title": {
        "en": "Measurand"
      }
    },
    "refs": {
      "$ref": "../features/refs.json",
      "title": {
        "en": "References",
        "pt": "Referências"
      }
    },
    "title": {
      "$ref": "../features/title.json",
      "description": {
        "en": "Human display title/label, consumed by the runtime that surfaces the thing to people. A single string, not i18n_text — a device label handed to a single-string config slot, not stored prose the system localizes.",
        "pt": "Rótulo de exibição humano emparelhado com um slug, consumido LITERALMENTE pelo runtime que apresenta a coisa às pessoas (friendly_name do HA). Uma única string, não i18n_text — um rótulo de dispositivo entregue a um slot de config de string única, não prosa armazenada que o sistema localiza."
      },
      "title": {
        "en": "Title - friendly name",
        "pt": "Nome amigável"
      }
    }
  }
}
